{"students": {"2014751125": {"name": "Tawfiq", "age": 22, "address": "Aftabnagar", "grades": {"Physics": "A+", "Bangla": "A+"}, "courses": ["Physics", "Bangla"]}, "2014751252": {"name": "Shaan", "age": 25, "address": "Khilgaon", "grades": {"Physics": "A+"}, "courses": ["Physics"]}, "2014751299": {"name": "Rakib", "age": 23, "address": "Rampura", "grades": {"Bangla": "A"}, "courses": ["Bangla"]}}, "courses": {"101": {"course_name": "Physics", "instructor": "Dr Khan", "students": ["Tawfiq", "Shaan"]}, "1001": {"course_name": "Bangla", "instructor": "Shajib Ahmed", "students": ["Rakib", "Tawfiq"]}}}